django2_url_robots/__init__.py
django2_url_robots/utils.py
django2_url_robots/views.py
django2_url_robots/templates/robots.txt
django2_url_robots/tests/__init__.py
django2_url_robots/tests/tests.py
django2_url_robots/tests/urls.py
django2_url_robots/tests/urls_profile.py
django2_url_robots-3.2.2.dist-info/AUTHORS.txt
django2_url_robots-3.2.2.dist-info/LICENSE
django2_url_robots-3.2.2.dist-info/METADATA
django2_url_robots-3.2.2.dist-info/WHEEL
django2_url_robots-3.2.2.dist-info/top_level.txt
django2_url_robots-3.2.2.dist-info/RECORD
