Metadata-Version: 2.1
Name: django2-url-robots
Version: 3.2.2
Summary: Django robots.txt generator
Home-page: https://github.com/maximekl/django2-url-robots
Author: Maxime Klampas
Author-email: mklampas@gmail.com
License: Python Software Foundation License
Platform: any
Classifier: Development Status :: 5 - Production/Stable
Classifier: Intended Audience :: Developers
Classifier: License :: OSI Approved :: Python Software Foundation License
Classifier: Natural Language :: English
Classifier: Operating System :: OS Independent
Classifier: Programming Language :: Python
Classifier: Environment :: Web Environment
Classifier: Framework :: Django
